apimatic_core/__init__.py
apimatic_core/api_call.py
apimatic_core/request_builder.py
apimatic_core/response_handler.py
apimatic_core/authentication/__init__.py
apimatic_core/authentication/header_auth.py
apimatic_core/authentication/query_auth.py
apimatic_core/authentication/multiple/__init__.py
apimatic_core/authentication/multiple/and_auth_group.py
apimatic_core/authentication/multiple/auth_group.py
apimatic_core/authentication/multiple/or_auth_group.py
apimatic_core/authentication/multiple/single_auth.py
apimatic_core/configurations/__init__.py
apimatic_core/configurations/endpoint_configuration.py
apimatic_core/configurations/global_configuration.py
apimatic_core/constants/__init__.py
apimatic_core/constants/logger_constants.py
apimatic_core/decorators/__init__.py
apimatic_core/decorators/lazy_property.py
apimatic_core/exceptions/__init__.py
apimatic_core/exceptions/anyof_validation_exception.py
apimatic_core/exceptions/auth_validation_exception.py
apimatic_core/exceptions/oneof_validation_exception.py
apimatic_core/factories/__init__.py
apimatic_core/factories/http_response_factory.py
apimatic_core/http/__init__.py
apimatic_core/http/http_call_context.py
apimatic_core/http/http_callback.py
apimatic_core/http/configurations/__init__.py
apimatic_core/http/configurations/http_client_configuration.py
apimatic_core/http/configurations/proxy_settings.py
apimatic_core/http/request/__init__.py
apimatic_core/http/request/http_request.py
apimatic_core/http/response/__init__.py
apimatic_core/http/response/api_response.py
apimatic_core/http/response/http_response.py
apimatic_core/logger/__init__.py
apimatic_core/logger/default_logger.py
apimatic_core/logger/sdk_logger.py
apimatic_core/logger/configuration/__init__.py
apimatic_core/logger/configuration/api_logging_configuration.py
apimatic_core/pagination/__init__.py
apimatic_core/pagination/paginated_data.py
apimatic_core/pagination/pagination_strategy.py
apimatic_core/pagination/strategies/__init__.py
apimatic_core-0.2.22.dist-info/licenses/LICENSE
apimatic_core-0.2.22.dist-info/METADATA
apimatic_core-0.2.22.dist-info/WHEEL
apimatic_core-0.2.22.dist-info/top_level.txt
apimatic_core-0.2.22.dist-info/RECORD
