Metadata-Version: 2.4
Name: apimatic-core
Version: 0.2.22
Summary: A library that contains core logic and utilities for consuming REST APIs using Python SDKs generated by APIMatic.
Home-page: https://github.com/apimatic/core-lib-python
Author: APIMatic
Author-email: support@apimatic.io
License: MIT
License-File: LICENSE
Requires-Dist: apimatic-core-interfaces~=0.1.0
Requires-Dist: jsonpickle~=3.3.0
Requires-Dist: python-dateutil~=2.8
Requires-Dist: requests~=2.31
Requires-Dist: setuptools>=68.0.0
Requires-Dist: jsonpointer~=2.3
Dynamic: author
Dynamic: author-email
Dynamic: description
Dynamic: description-content-type
Dynamic: home-page
Dynamic: license
Dynamic: license-file
Dynamic: requires-dist
Dynamic: summary
